.installed.cfg
bootstrap.py
buildout.cfg
setup.cfg
setup.py
docs/HISTORY.txt
z3c/__init__.py
z3c.amf.egg-info/PKG-INFO
z3c.amf.egg-info/SOURCES.txt
z3c.amf.egg-info/dependency_links.txt
z3c.amf.egg-info/namespace_packages.txt
z3c.amf.egg-info/not-zip-safe
z3c.amf.egg-info/requires.txt
z3c.amf.egg-info/top_level.txt
z3c/amf/HTTPRequest.py
z3c/amf/README.txt
z3c/amf/__init__.py
z3c/amf/amfgateway.py
z3c/amf/configure.zcml
z3c/amf/ftesting.zcml
z3c/amf/ftests.py
z3c/amf/interfaces.py
z3c/amf/meta.zcml
z3c/amf/metaconfigure.py
z3c/amf/metadirectives.py
z3c/amf/patch.py
z3c/amf/permissions.py
z3c/amf/testView.py
z3c/amf/browser/__init__.py
z3c/amf/browser/configure.zcml
z3c/amf/browser/crossdomain.xml
z3c/amf/tests/__init__.py
z3c/amf/tests/amf.zcml
z3c/amf/tests/amf_error.zcml
z3c/amf/tests/test_directives.py