Metadata-Version: 1.0
Name: z3c.amf
Version: 0.2
Summary: Zope support for Flash messages (AMF)
Home-page: http://svn.zope.org/z3c.amf
Author: Jean-Francois Roche
Author-email: jfroche@affinitic.be
License: ZPL 2.1
Keywords: Zope2 Zope AMF Flash Flex
Platform: UNKNOWN
Classifier: Environment :: Web Environment
Classifier: Framework :: Zope2
Classifier: Framework :: Zope3
Classifier: License :: OSI Approved :: Zope Public License
Classifier: Operating System :: OS Independent
Classifier: Programming Language :: Python
Classifier: Topic :: Internet :: WWW/HTTP :: Site Management
Classifier: Programming Language :: Python
Classifier: Topic :: Software Development :: Libraries :: Python Modules
